[
    {"title": "Mládek - Jožin z bažin", "file": "jozin.html"},
    {"title": "S&U - Statistika", "file": "statistika.html"},
    {"title": "Záviš - Zbyl jsem tu sám", "file": "zbyljsemtusam.html"},
    {"title": "Záviš - Červený most", "file": "cervenymost.html"},
    {"title": "Záviš - Už je to tak", "file": "uzjetotak.html"},
    {"title": "Záviš - Nákup", "file": "nakup.html"},
    {"title": "Nohavica - Hlídač krav", "file": "Nohavica - Hlídač krav.html"},
    {"title": "Nohavica - Dokud se zpívá", "file": "Nohavica - Dokud se zpívá.html"},
    {"title": "Nohavica - Tři Čuníci", "file": "Nohavica - Tři Čuníci.html"},
    {"title": "Nohavica - Darmoděj", "file": "Nohavica - Darmoděj.html"},
    {"title": "Nohavica - Kozel", "file": "Nohavica - Kozel.html"},
    {"title": "Nohavica - Pijte vodu", "file": "Nohavica - Pijte vodu.html"},
    {"title": "Nohavica - Zítra ráno v pět", "file": "Nohavica - Zítra ráno v pět.html"},
    {"title": "Nohavica - Tramp", "file": "Nohavica - Tramp.html"},
    {"title": "Premier - Hrobař", "file": "Premier - Hrobař.html"},
    {"title": "Olympic - Slzy tvý mámy", "file": "Olympic - Slzy tvý mámy.html"},
    {"title": "Olympic - Želva", "file": "Olympic - Želva.html"},
    {"title": "Olympic - Dej mi víc své lásky", "file": "Olympic - Dej mi víc své lásky.html"},
    {"title": "Olympic - Jasná zpráva", "file": "Olympic - Jasná zpráva.html"},
    {"title": "Olympic - Otázky", "file": "Olympic - Otázky.html"},
    {"title": "Tučný - Báječná ženská", "file": "Tučný - Báječná ženská.html"},
    {"title": "Tučný - Všichni jsou už v Mexiku", "file": "Tučný - Všichni jsou už v Mexiku.html"},
    {"title": "Tučný - Prodavač", "file": "Tučný - Prodavač.html"},
    {"title": "Rivola - Bedna od whisky", "file": "Rivola - Bedna od whisky.html"},
    {"title": "Janoušek - Škoda 1000mb", "file": "Janoušek - Škoda 1000mb.html"},
    {"title": "Matuška - Slavíci z madridu", "file": "Matuška - Slavíci z madridu.html"},
    {"title": "Matuška - Jó třešně zrály", "file": "Matuška - Jó třešně zrály.html"},
    {"title": "Matuška - Růže z texasu", "file": "Matuška - Růže z texasu.html"},
    {"title": "Nohavica - Jdou po mně jdou", "file": "Nohavica - Jdou po mně jdou.html"}
]